setup.py
bybop/Bybop_Commands.py
bybop/Bybop_Connection.py
bybop/Bybop_Device.py
bybop/Bybop_Discovery.py
bybop/Bybop_Network.py
bybop/Bybop_NetworkAL.py
bybop/__init__.py
bybop.egg-info/PKG-INFO
bybop.egg-info/SOURCES.txt
bybop.egg-info/dependency_links.txt
bybop.egg-info/not-zip-safe
bybop.egg-info/requires.txt
bybop.egg-info/top_level.txt